jebao/__init__.py
jebao/const.py
jebao/device.py
jebao/discovery.py
jebao/exceptions.py
jebao/mdp20000.py
jebao/protocol.py
jebao/retry.py
python_jebao-0.1.5.dist-info/licenses/LICENSE
python_jebao-0.1.5.dist-info/METADATA
python_jebao-0.1.5.dist-info/WHEEL
python_jebao-0.1.5.dist-info/top_level.txt
python_jebao-0.1.5.dist-info/RECORD
