Metadata-Version: 2.4
Name: python-jebao
Version: 0.1.5
Summary: Python library for controlling Jebao aquarium pumps
Home-page: https://github.com/jrigling/python-jebao
Author: Justin Rigling
Author-email: Justin Rigling <jrigling@gmail.com>
License-Expression: MIT
Project-URL: Homepage, https://github.com/jrigling/python-jebao
Project-URL: Repository, https://github.com/jrigling/python-jebao
Project-URL: Issues, https://github.com/jrigling/python-jebao/issues
Project-URL: Documentation, https://github.com/jrigling/python-jebao#readme
Keywords: jebao,aquarium,pump,home-assistant,iot
Classifier: Development Status :: 3 - Alpha
Classifier: Intended Audience :: Developers
Classifier: Operating System :: OS Independent
Classifier: Programming Language :: Python :: 3
Classifier: Programming Language :: Python :: 3.9
Classifier: Programming Language :: Python :: 3.10
Classifier: Programming Language :: Python :: 3.11
Classifier: Programming Language :: Python :: 3.12
Classifier: Programming Language :: Python :: 3.13
Classifier: Topic :: Home Automation
Classifier: Topic :: Software Development :: Libraries :: Python Modules
Requires-Python: >=3.9
License-File: LICENSE
Requires-Dist: netifaces>=0.11.0
Provides-Extra: dev
Requires-Dist: pytest>=7.0; extra == "dev"
Requires-Dist: pytest-asyncio>=0.21.0; extra == "dev"
Requires-Dist: pytest-cov>=4.0; extra == "dev"
Requires-Dist: black>=23.0; extra == "dev"
Requires-Dist: ruff>=0.1.0; extra == "dev"
Requires-Dist: mypy>=1.0; extra == "dev"
Provides-Extra: build
Requires-Dist: build>=0.10.0; extra == "build"
Requires-Dist: twine>=4.0.0; extra == "build"
Dynamic: author
Dynamic: home-page
Dynamic: license-file
Dynamic: requires-python
